{
  "required": true,
  "minVersion": "0.8",
  "package": "com.minhcraft.createlesstrains.mixin",
  "compatibilityLevel": "JAVA_17",
  "mixins": [
    "block.AllBlockEntityTypesMixin",
    "block.AllBlocksMixin",
    "block.FlapDisplayBlockEntityMixin",
    "block.FlapDisplayBlockMixin",
    "block.StationBlockMixin",
    "block.WhistleBlockEntityMixin",
    "block.WhistleBlockMixin",
    "block.helper.StationBlockEntityAccessor",
    "embeddium_compat.SodiumCompatMixin",
    "ponder.AllCreatePonderScenesMixin",
    "ponder.AllCreatePonderTagsMixin",
    "ponder.scenes.DisplayScenesMixin",
    "ponder.scenes.RedstoneScenesMixin",
    "ponder.scenes.SteamScenesMixin",
    "ponder.scenes.TrackObserverScenesMixin",
    "ponder.scenes.TrackScenesMixin",
    "ponder.scenes.TrainScenesMixin",
    "ponder.scenes.TrainStationScenesMixin",
    "schedule.ScheduleMixin"
  ],
  "client": [
  ],
  "injectors": {
    "defaultRequire": 1
  }
}
